Workbook

Sheet Historicals
A1: Greggs DCF - Historicals
A3: £m | B3: 2022 | C3: 2023 | D3: 2024
A5: Revenue | B5: 1512.8 | C5: 1809.6 | D5: 2014.2
A6: Operating Profit | B6: 154.4 | C6: 171.7 | D6: 195.3
A7: D&A | B7: 115.5 | C7: 125 | D7: 140
A8: Capex | B8: 103.3 | C8: 198.1 | D8: 240.9
A9: Tax Paid | B9: 13.3 | C9: 11.9 | D9: 27.7
A10: Net debt | B10: -191.6 | C10: -195.3 | D10: -125.3
A11: Shares (m) | B11: 102.3 | C11: 102.3 | D11: 102.6
A12: Share Price | D12: 19.15 | F12: Share proce 06/08/2026, LSE:GRG, pence converted to £

Sheet Sensitivity 
A1: Sensitivity – Implied Value per Share (£)
A2: WACC \ Terminal growth | C2: 0.01 | D2: 0.015 | E2: 0.02 | F2: 0.025 | G2: 0.03
B3: 0.0869 | C3: {=(SUMPRODUCT($B$11:$F$11/(1+$B3)^$B$12:$F$12)+$F$11*(1+C$2)/($B3-C$2)/(1+$B3)^5-$B$13)/$B$14} -> 10.218891 | D3: {=(SUMPRODUCT($B$11:$F$11/(1+$B3)^$B$12:$F$12)+$F$11*(1+D$2)/($B3-D$2)/(1+$B3)^5-$B$13)/$B$14} -> 10.704854 | E3: {=(SUMPRODUCT($B$11:$F$11/(1+$B3)^$B$12:$F$12)+$F$11*(1+E$2)/($B3-E$2)/(1+$B3)^5-$B$13)/$B$14} -> 11.263458 | F3: {=(SUMPRODUCT($B$11:$F$11/(1+$B3)^$B$12:$F$12)+$F$11*(1+F$2)/($B3-F$2)/(1+$B3)^5-$B$13)/$B$14} -> 11.912305 | G3: {=(SUMPRODUCT($B$11:$F$11/(1+$B3)^$B$12:$F$12)+$F$11*(1+G$2)/($B3-G$2)/(1+$B3)^5-$B$13)/$B$14} -> 12.675185
B4: 0.0969 | C4: {=(SUMPRODUCT($B$11:$F$11/(1+$B4)^$B$12:$F$12)+$F$11*(1+C$2)/($B4-C$2)/(1+$B4)^5-$B$13)/$B$14} -> 9.1470466 | D4: {=(SUMPRODUCT($B$11:$F$11/(1+$B4)^$B$12:$F$12)+$F$11*(1+D$2)/($B4-D$2)/(1+$B4)^5-$B$13)/$B$14} -> 9.5109998 | E4: {=(SUMPRODUCT($B$11:$F$11/(1+$B4)^$B$12:$F$12)+$F$11*(1+E$2)/($B4-E$2)/(1+$B4)^5-$B$13)/$B$14} -> 9.9222811 | F4: {=(SUMPRODUCT($B$11:$F$11/(1+$B4)^$B$12:$F$12)+$F$11*(1+F$2)/($B4-F$2)/(1+$B4)^5-$B$13)/$B$14} -> 10.390764 | G4: {=(SUMPRODUCT($B$11:$F$11/(1+$B4)^$B$12:$F$12)+$F$11*(1+G$2)/($B4-G$2)/(1+$B4)^5-$B$13)/$B$14} -> 10.929275
B5: ='DCF model '!B9 -> 0.1069 | C5: {=(SUMPRODUCT($B$11:$F$11/(1+$B5)^$B$12:$F$12)+$F$11*(1+C$2)/($B5-C$2)/(1+$B5)^5-$B$13)/$B$14} -> 8.2975952 | D5: {=(SUMPRODUCT($B$11:$F$11/(1+$B5)^$B$12:$F$12)+$F$11*(1+D$2)/($B5-D$2)/(1+$B5)^5-$B$13)/$B$14} -> 8.5781027 | E5: {=(SUMPRODUCT($B$11:$F$11/(1+$B5)^$B$12:$F$12)+$F$11*(1+E$2)/($B5-E$2)/(1+$B5)^5-$B$13)/$B$14} -> 8.8908896 | F5: {=(SUMPRODUCT($B$11:$F$11/(1+$B5)^$B$12:$F$12)+$F$11*(1+F$2)/($B5-F$2)/(1+$B5)^5-$B$13)/$B$14} -> 9.2418677 | G5: {=(SUMPRODUCT($B$11:$F$11/(1+$B5)^$B$12:$F$12)+$F$11*(1+G$2)/($B5-G$2)/(1+$B5)^5-$B$13)/$B$14} -> 9.6384868
B6: 0.1169 | C6: {=(SUMPRODUCT($B$11:$F$11/(1+$B6)^$B$12:$F$12)+$F$11*(1+C$2)/($B6-C$2)/(1+$B6)^5-$B$13)/$B$14} -> 7.608076 | D6: {=(SUMPRODUCT($B$11:$F$11/(1+$B6)^$B$12:$F$12)+$F$11*(1+D$2)/($B6-D$2)/(1+$B6)^5-$B$13)/$B$14} -> 7.8292878 | E6: {=(SUMPRODUCT($B$11:$F$11/(1+$B6)^$B$12:$F$12)+$F$11*(1+E$2)/($B6-E$2)/(1+$B6)^5-$B$13)/$B$14} -> 8.0733285 | F6: {=(SUMPRODUCT($B$11:$F$11/(1+$B6)^$B$12:$F$12)+$F$11*(1+F$2)/($B6-F$2)/(1+$B6)^5-$B$13)/$B$14} -> 8.3439242 | G6: {=(SUMPRODUCT($B$11:$F$11/(1+$B6)^$B$12:$F$12)+$F$11*(1+G$2)/($B6-G$2)/(1+$B6)^5-$B$13)/$B$14} -> 8.6456587
B7: 0.1269 | C7: {=(SUMPRODUCT($B$11:$F$11/(1+$B7)^$B$12:$F$12)+$F$11*(1+C$2)/($B7-C$2)/(1+$B7)^5-$B$13)/$B$14} -> 7.0374035 | D7: {=(SUMPRODUCT($B$11:$F$11/(1+$B7)^$B$12:$F$12)+$F$11*(1+D$2)/($B7-D$2)/(1+$B7)^5-$B$13)/$B$14} -> 7.2151623 | E7: {=(SUMPRODUCT($B$11:$F$11/(1+$B7)^$B$12:$F$12)+$F$11*(1+E$2)/($B7-E$2)/(1+$B7)^5-$B$13)/$B$14} -> 7.4095497 | F7: {=(SUMPRODUCT($B$11:$F$11/(1+$B7)^$B$12:$F$12)+$F$11*(1+F$2)/($B7-F$2)/(1+$B7)^5-$B$13)/$B$14} -> 7.6230134 | G7: {=(SUMPRODUCT($B$11:$F$11/(1+$B7)^$B$12:$F$12)+$F$11*(1+G$2)/($B7-G$2)/(1+$B7)^5-$B$13)/$B$14} -> 7.8585063
A10: Model links
A11: Free cash flow (£m) | B11: ='DCF model '!B23 -> 56.558736 | C11: ='DCF model '!C23 -> 61.083435 | D11: ='DCF model '!D23 -> 65.97011 | E11: ='DCF model '!E23 -> 71.247718 | F11: ='DCF model '!F23 -> 76.947536
A12: Year | B12: 1 | C12: 2 | D12: 3 | E12: 4 | F12: 5
A13: Net debt / (cash) (£m) | B13: =Historicals!D10 -> -125.3
A14: Shares outstanding (m) | B14: =Historicals!D11 -> 102.6

Sheet DCF model 
A1: Greggs DCF Model
A2: Greggs DCF – Assumptions | B2: Input | C2: Reasoning / Source | F2: WACC BUILD | H2: Input | I2: Reasoning / Source
A3: Revenue growth | B3: 0.08 | C3: Below the recent 11% as growth slows; still expanding shops | F3: Risk-free rate | H3: 0.0494 | I3: UK 10-year government bond yield.
A4: EBIT margin | B4: 0.098 | C4: 3-year average; margins have been stable | F4: Beta | H4: 1.15 | I4: How much the share moves vs the market. ~1.15 over 5 years.
A5: Tax rate | B5: 0.25 | C5: UK corporation tax rate. | F5: Equity risk premium | H5: 0.05 | I5: Extra return investors want for holding shares instead of safe government bonds. ~5% is the standard UK assumption.
A6: D&A % of revenue | B6: 0.07 | C6: Recent years ran ~7%; held flat | F6: Cost of equity | H6: =H3+H4*H5 -> 0.1069 | I6: Risk-free + beta × risk premium (CAPM). The return shareholders require.
A7: Capex % of revenue | B7: 0.115 | C7: Recent 2-year average; capex is high due to shop expansion | F7: Cost of debt (after tax) | H7: 0.03 | I7: Interest rate after tax. ~3%, but immaterial — Greggs has almost no debt.
A8: Working capital % of revenue | B8: 0.0025 | C8: Tiny — Greggs takes cash at the till, so little is tied up | F8: Equity weight | H8: 1 | I8: Share of funding from equity. ~100% for Greggs.
A9: WACC | B9: =H10 -> 0.1069 | C9: The discount rate; built in the WACC block to the right. | F9: Debt weight | H9: 0 | I9: Share from debt. ~0% — Greggs is essentially all-equity funded.
A10: Terminal growth | B10: 0.02 | C10: Long-run growth after year 5. Set near UK GDP/inflation (~2%). Can't exceed GDP forever, or Greggs would outgrow the economy. | F10: WACC | H10: =H8*H6+H9*H7 -> 0.1069 | I10: Blended required return used to discount free cash flows.
A13: Forecast Free Cash Flow
B14: Year 1 | C14: Year 2 | D14: Year 3 | E14: Year 4 | F14: Year 5
A15: Revenue | B15: =Historicals!D5*(1+'DCF model '!$B$3) -> 2175.336 | C15: =B15*(1+$B$3) -> 2349.3629 | D15: =C15*(1+$B$3) -> 2537.3119 | E15: =D15*(1+$B$3) -> 2740.2969 | F15: =E15*(1+$B$3) -> 2959.5206
A16: EBITDA | B16: =B17+(B15*$B$6) -> 365.45645 | C16: =C17+(C15*$B$6) -> 394.69296 | D16: =D17+(D15*$B$6) -> 426.2684 | E16: =E17+(E15*$B$6) -> 460.36987 | F16: =F17+(F15*$B$6) -> 497.19946
A17: EBIT | B17: =B15*$B$4 -> 213.18293 | C17: =C15*$B$4 -> 230.23756 | D17: =D15*$B$4 -> 248.65657 | E17: =E15*$B$4 -> 268.54909 | F17: =F15*$B$4 -> 290.03302
A18: Tax | B18: =-B17*$B$5 -> -53.295732 | C18: =-C17*$B$5 -> -57.559391 | D18: =-D17*$B$5 -> -62.164142 | E18: =-E17*$B$5 -> -67.137273 | F18: =-F17*$B$5 -> -72.508255
A19: NOPAT | B19: =B17+B18 -> 159.8872 | C19: =C17+C18 -> 172.67817 | D19: =D17+D18 -> 186.49243 | E19: =E17+E18 -> 201.41182 | F19: =F17+F18 -> 217.52477
A20: Add: D&A | B20: =B15*$B$6 -> 152.27352 | C20: =C15*$B$6 -> 164.4554 | D20: =D15*$B$6 -> 177.61183 | E20: =E15*$B$6 -> 191.82078 | F20: =F15*$B$6 -> 207.16644
A21: Less: Capex | B21: =-B15*$B$7 -> -250.16364 | C21: =-C15*$B$7 -> -270.17673 | D21: =-D15*$B$7 -> -291.79087 | E21: =-E15*$B$7 -> -315.13414 | F21: =-F15*$B$7 -> -340.34487
A22: Less: WC increase | B22: =-B15*$B$8 -> -5.43834 | C22: =-C15*$B$8 -> -5.8734072 | D22: =-D15*$B$8 -> -6.3432798 | E22: =-E15*$B$8 -> -6.8507422 | F22: =-F15*$B$8 -> -7.3988015
A23: Free Cash Flow | B23: =B19+B20+B21+B22 -> 56.558736 | C23: =C19+C20+C21+C22 -> 61.083435 | D23: =D19+D20+D21+D22 -> 65.97011 | E23: =E19+E20+E21+E22 -> 71.247718 | F23: =F19+F20+F21+F22 -> 76.947536
A24: Discount factor | B24: =1/(1+$B$9)^1 -> 0.90342398 | C24: =1/(1+$B$9)^2 -> 0.81617488 | D24: =1/(1+$B$9)^3 -> 0.73735196 | E24: =1/(1+$B$9)^4 -> 0.66614144 | F24: =1/(1+$B$9)^5 -> 0.60180815
A25: PV of FCF | B25: =B23*B24 -> 51.096518 | C25: =C23*C24 -> 49.854765 | D25: =D23*D24 -> 48.64319 | E25: =E23*E24 -> 47.461058 | F25: =F23*F24 -> 46.307654
A27: Sum of Pv of FCP | B27: =SUM(B25:F25) -> 243.36318
A28: Terminal value | B28: =(F23*(1+$B$10))/($B$9-$B$10) -> 903.18166
A29: PV of Terminal Value | B29: =B28*F24 -> 543.54208
A30: Enterprise Value | B30: =B27+B29 -> 786.90527
A31: Equity Value | B31: =B30-Historicals!D10 -> 912.20527
A32: Value per Share (£) | B32: =B31/Historicals!D11 -> 8.8908896
A33: Current Price (£) | B33: =Historicals!D12 -> 19.15
A34: Upside/Downside | B34: =B32/B33-1 -> -0.53572378

Sheet Summary
A1: Summary
A2: Tab 1 - Historicals
A3: Purpose: The raw material. Actual figures, from Greggs annual report, which everything else is forecast from.
A5: Revenue, operating profit: from the consolidated income statement.
A6: D&A: from the cash flow statement: depreciation of property/equipment + depreciation of right of use + ammortisation, summed
A7: Capex — from investing activities: purchase of property, plant & equipment + intangibles. Entered as a positive number
A8: Tax — the actual cash 'income tax paid' line (not the accounting expense), which is more correct for a DCF
A9: Net debt — borrowings − cash. Greggs has no borrowings, so this is net cash (entered negative). Leases treated as an operating cost
A10: Shares — diluted weighted-average share count from the EPS note (~102.6m). Diluted is used for valuation
A11: Share price - today's live price (LSE: GRG), converted from pence to £. Only today's price is needed.
A13: Terminology
A14: DCF (Discounted Cash Flow) - A valuation method: a company is worth the cash it will generate in future, converted to today's value ('discounted') because money later is worth less than money now
... A22: Sensitivity analysis - A grid showing how value per share changed as WACC and terminal growth vary. Shows the answer is a range, not a single number
